MANIFEST.in
setup.py
Djserializers.egg-info/PKG-INFO
Djserializers.egg-info/SOURCES.txt
Djserializers.egg-info/dependency_links.txt
Djserializers.egg-info/not-zip-safe
Djserializers.egg-info/top_level.txt
djserializers/__init__.py
djserializers/annotated.py
djserializers/base.py
djserializers/json_renderer.py
djserializers/models.py
djserializers/tests.py
djserializers/util.py