Metadata-Version: 1.0
Name: Djserializers
Version: 0.9
Summary: Serializers for Django
Home-page: https://github.com/prestontimmons/serializers/
Author: Preston Timmons
Author-email: prestontimmons@gmail.com
License: UNKNOWN
Platform: UNKNOWN
Classifier: Development Status :: 4 - Beta
Classifier: Intended Audience :: Developers
Classifier: Framework :: Django
Classifier: License :: OSI Approved :: BSD License
